{
  "Available endpoints": {

  "GET /": {
    "description": "serves up a json representation of all the available endpoints of the api"
    },
  
  "GET /api/topics": {
    "description": "serves an array of all topics",
    "queries": []
    },

  "GET /api/users": {
    "description": "serves an array of all users",
    "queries": []
    },

  "GET /api/articles": {
    "description": "serves an array of all articles",
    "queries": ["author", "topic", "sort_by", "order"]
    },

  "GET /api/articles/:article_id": {
    "description": "serves a specific article",
    "parameters": ["article_id"]
    },

  "PATCH /api/articles/:article_id": {
    "description": "updates a specific article",
    "parameters": ["article_id"]
    },
  
  "GET /api/articles/:article_id/comments": {
    "description": "gets the comments related to a specific article",
    "parameters": ["article_id"]  
    },
  
  "POST /api/articles/:article_id/comments": {
    "description": "adds a comment to a specific article",
    "parameters": ["article_id"]  
    },

  "DELETE /api/articles/:article_id/comments": {
    "description": "deletes a comment related to a specific article",
    "parameters": ["article_id"]  
    }
  }
}

